commonroad_helper_functions/__init__.py
commonroad_helper_functions/collision_check.py
commonroad_helper_functions/customvehicleicons.py
commonroad_helper_functions/exceptions.py
commonroad_helper_functions/interpolation.py
commonroad_helper_functions/logger.py
commonroad_helper_functions/sensor_model.py
commonroad_helper_functions/spacial.py
commonroad_helper_functions/visualization.py
commonroad_helper_functions/utils/__init__.py
commonroad_helper_functions/utils/cubicspline.py
commonroad_helper_functions-1.0.0.dist-info/LICENSE
commonroad_helper_functions-1.0.0.dist-info/METADATA
commonroad_helper_functions-1.0.0.dist-info/WHEEL
commonroad_helper_functions-1.0.0.dist-info/top_level.txt
commonroad_helper_functions-1.0.0.dist-info/RECORD
