Metadata-Version: 2.1
Name: commonroad-helper-functions
Version: 1.0.0
Summary: Additional supplement functions to CommonRoad
Home-page: UNKNOWN
License: UNKNOWN
Platform: UNKNOWN
Classifier: Programming Language :: Python :: 3
Classifier: Operating System :: OS Independent
Requires-Python: >=3.6
